Workbook

Sheet Sales Data
A1: Order_ID | B1: Order_Date | C1: Customer_ID | D1: Product_ID | E1: Region | F1: Salesperson | G1: Channel | H1: Quantity | I1: Unit_Price | J1: Discount | K1: Payment_Method | M1: Gross Sales | N1: Discount Amount | O1: Net Sales | P1: Product Cost | Q1: Profit | R1: Profit Margin | S1: Customer Name
A2: ORD1001 | B2: 45660 | C2: CUST001 | D2: P101 | E2: North | F2: Rahul | G2: Online | H2: 3 | I2: 1200 | J2: 0.05 | K2: UPI | M2: =H2*I2 -> 3600 | N2: =M2*J2 -> 180 | O2: =M2-N2 -> 3420 | P2: =VLOOKUP(D2, Products!A:E,4,FALSE) -> 700 | Q2: =O2-(H2*P2) -> 1320 | R2: =(Q2/O2)*100 -> 38.596491 | S2: =VLOOKUP(C2, Customers!A:F, 2,FALSE) -> Aarav Sharma
A3: ORD1002 | B3: 45661 | C3: CUST002 | D3: P103 | E3: West | F3: Priya | G3: Store | H3: 2 | I3: 2500 | J3: 0.1 | K3: Credit Card | M3: =H3*I3 -> 5000 | N3: =M3*J3 -> 500 | O3: =M3-N3 -> 4500 | P3: =VLOOKUP(D3, Products!A:E,4,FALSE) -> 1400 | Q3: =O3-(H3*P3) -> 1700 | R3: =(Q3/O3)*100 -> 37.777778 | S3: =VLOOKUP(C3, Customers!A:F, 2,FALSE) -> Diya Patel
A4: ORD1003 | B4: 45662 | C4: CUST003 | D4: P102 | E4: South | F4: Amit | G4: Online | H4: 5 | I4: 800 | J4: 0 | K4: UPI | M4: =H4*I4 -> 4000 | N4: =M4*J4 -> 0 | O4: =M4-N4 -> 4000 | P4: =VLOOKUP(D4, Products!A:E,4,FALSE) -> 450 | Q4: =O4-(H4*P4) -> 1750 | R4: =(Q4/O4)*100 -> 43.75 | S4: =VLOOKUP(C4, Customers!A:F, 2,FALSE) -> Rohan Mehta
A5: ORD1004 | B5: 45664 | C5: CUST004 | D5: P105 | E5: East | F5: Neha | G5: Store | H5: 1 | I5: 4500 | J5: 0.15 | K5: Cash | M5: =H5*I5 -> 4500 | N5: =M5*J5 -> 675 | O5: =M5-N5 -> 3825 | P5: =VLOOKUP(D5, Products!A:E,4,FALSE) -> 2800 | Q5: =O5-(H5*P5) -> 1025 | R5: =(Q5/O5)*100 -> 26.797386 | S5: =VLOOKUP(C5, Customers!A:F, 2,FALSE) -> Ananya Shah
A6: ORD1005 | B6: 45666 | C6: CUST005 | D6: P104 | E6: North | F6: Rahul | G6: Online | H6: 4 | I6: 1500 | J6: 0.05 | K6: Credit Card | M6: =H6*I6 -> 6000 | N6: =M6*J6 -> 300 | O6: =M6-N6 -> 5700 | P6: =VLOOKUP(D6, Products!A:E,4,FALSE) -> 9000 | Q6: =O6-(H6*P6) -> -30300 | R6: =(Q6/O6)*100 -> -531.57895 | S6: =VLOOKUP(C6, Customers!A:F, 2,FALSE) -> Vivaan Desai
A7: ORD1006 | B7: 45668 | C7: CUST006 | D7: P101 | E7: West | F7: Priya | G7: Store | H7: 6 | I7: 1200 | J7: 0.1 | K7: UPI | M7: =H7*I7 -> 7200 | N7: =M7*J7 -> 720 | O7: =M7-N7 -> 6480 | P7: =VLOOKUP(D7, Products!A:E,4,FALSE) -> 700 | Q7: =O7-(H7*P7) -> 2280 | R7: =(Q7/O7)*100 -> 35.185185 | S7: =VLOOKUP(C7, Customers!A:F, 2,FALSE) -> Ishita Joshi
A8: ORD1007 | B8: 45670 | C8: CUST007 | D8: P106 | E8: South | F8: Amit | G8: Online | H8: 2 | I8: 3200 | J8: 0 | K8: Credit Card | M8: =H8*I8 -> 6400 | N8: =M8*J8 -> 0 | O8: =M8-N8 -> 6400 | P8: =VLOOKUP(D8, Products!A:E,4,FALSE) -> 1800 | Q8: =O8-(H8*P8) -> 2800 | R8: =(Q8/O8)*100 -> 43.75 | S8: =VLOOKUP(C8, Customers!A:F, 2,FALSE) -> Arjun Kapoor
A9: ORD1008 | B9: 45672 | C9: CUST008 | D9: P103 | E9: East | F9: Neha | G9: Store | H9: 3 | I9: 2500 | J9: 0.05 | K9: Cash | M9: =H9*I9 -> 7500 | N9: =M9*J9 -> 375 | O9: =M9-N9 -> 7125 | P9: =VLOOKUP(D9, Products!A:E,4,FALSE) -> 1400 | Q9: =O9-(H9*P9) -> 2925 | R9: =(Q9/O9)*100 -> 41.052632 | S9: =VLOOKUP(C9, Customers!A:F, 2,FALSE) -> Meera Rao
A10: ORD1009 | B10: 45675 | C10: CUST009 | D10: P102 | E10: North | F10: Rahul | G10: Online | H10: 7 | I10: 800 | J10: 0.1 | K10: UPI | M10: =H10*I10 -> 5600 | N10: =M10*J10 -> 560 | O10: =M10-N10 -> 5040 | P10: =VLOOKUP(D10, Products!A:E,4,FALSE) -> 450 | Q10: =O10-(H10*P10) -> 1890 | R10: =(Q10/O10)*100 -> 37.5 | S10: =VLOOKUP(C10, Customers!A:F, 2,FALSE) -> Kabir Singh
A11: ORD1010 | B11: 45677 | C11: CUST010 | D11: P105 | E11: West | F11: Priya | G11: Store | H11: 2 | I11: 4500 | J11: 0.15 | K11: Credit Card | M11: =H11*I11 -> 9000 | N11: =M11*J11 -> 1350 | O11: =M11-N11 -> 7650 | P11: =VLOOKUP(D11, Products!A:E,4,FALSE) -> 2800 | Q11: =O11-(H11*P11) -> 2050 | R11: =(Q11/O11)*100 -> 26.797386 | S11: =VLOOKUP(C11, Customers!A:F, 2,FALSE) -> Sara Khan
A12: ORD1011 | B12: 45679 | C12: CUST001 | D12: P104 | E12: South | F12: Amit | G12: Online | H12: 5 | I12: 1500 | J12: 0.05 | K12: UPI | M12: =H12*I12 -> 7500 | N12: =M12*J12 -> 375 | O12: =M12-N12 -> 7125 | P12: =VLOOKUP(D12, Products!A:E,4,FALSE) -> 9000 | Q12: =O12-(H12*P12) -> -37875 | R12: =(Q12/O12)*100 -> -531.57895 | S12: =VLOOKUP(C12, Customers!A:F, 2,FALSE) -> Aarav Sharma
A13: ORD1012 | B13: 45682 | C13: CUST002 | D13: P106 | E13: East | F13: Neha | G13: Store | H13: 1 | I13: 3200 | J13: 0 | K13: Cash | M13: =H13*I13 -> 3200 | N13: =M13*J13 -> 0 | O13: =M13-N13 -> 3200 | P13: =VLOOKUP(D13, Products!A:E,4,FALSE) -> 1800 | Q13: =O13-(H13*P13) -> 1400 | R13: =(Q13/O13)*100 -> 43.75 | S13: =VLOOKUP(C13, Customers!A:F, 2,FALSE) -> Diya Patel
... A31: ORD1030 | B31: 45733 | C31: CUST010 | D31: P102 | E31: West | F31: Priya | G31: Store | H31: 8 | I31: 800 | J31: 0.15 | K31: Cash | M31: =H31*I31 -> 6400 | N31: =M31*J31 -> 960 | O31: =M31-N31 -> 5440 | P31: =VLOOKUP(D31, Products!A:E,4,FALSE) -> 450 | Q31: =O31-(H31*P31) -> 1840 | R31: =(Q31/O31)*100 -> 33.823529 | S31: =VLOOKUP(C31, Customers!A:F, 2,FALSE) -> Sara Khan
A34: Total Net Sales = | C34: =SUM(O2:O31) -> 193260
A35: Calculaate Total Profit = | D35: =SUM(Q2:Q31) -> -146690
A36: Calculate Average order value = | D36: =AVERAGE(O2:O31) -> 6442
A37: Find the highest net sales from one order = | E37: =MAX(O2:O31) -> 11250
A38: Find the Lowest net sales from one order = | E38: =MIN(O2:O31) -> 2400
A39: How many orders are there = | D39: =COUNTA(A2:A31) -> 30
A40: How many orders made through Online = | E40: =COUNTIF(G2:G31, "Online") -> 15
A41: How many orders were made offline = | E41: =COUNTIF(G2:G31, "Store") -> 15
A42: What is the total quantity sold = | D42: =SUM(H2:H31) -> 117
A43: What is the average quantity per order = | E43: =AVERAGE(H2:H31) -> 3.9
A44: Total Net Sales for North region = | D44: =SUMIF(E2:E31, "North",O2:O31) -> 53580
A45: Total net sales for Online = | D45: =SUMIF(G2:G31, "Online", O2:O31) -> 91220
A46: Total profit by Rahul = | C46: =SUMIF(F2:F31, "Rahul", Q2:Q31) -> -61070

Sheet Products
A1: Product_ID | B1: Product_Name | C1: Category | D1: Cost_Price | E1: Supplier | F1: total quantity sold
A2: P101 | B2: Laptop Stand | C2: Accessories | D2: 700 | E2: TechWorld | F2: =SUMIF('Sales Data'!D2:D31, Products!A2, 'Sales Data'!H2:H31) -> 25
A3: P102 | B3: Wireless Mouse | C3: Accessories | D3: 450 | E3: CompuMart | F3: =SUMIF('Sales Data'!D3:D32, Products!A3, 'Sales Data'!H3:H32) -> 29
A4: P103 | B4: Mechanical Keyboard | C4: Accessories | D4: 1400 | E4: KeyTech | F4: =SUMIF('Sales Data'!D4:D33, Products!A4, 'Sales Data'!H4:H33) -> 14
A5: P104 | B5: Monitor | C5: Electronics | D5: 9000 | E5: DisplayHub | F5: =SUMIF('Sales Data'!D5:D34, Products!A5, 'Sales Data'!H5:H34) -> 27
A6: P105 | B6: Office Chair | C6: Furniture | D6: 2800 | E6: FurniPro | F6: =SUMIF('Sales Data'!D6:D35, Products!A6, 'Sales Data'!H6:H35) -> 7
A7: P106 | B7: Desk Lamp | C7: Electronics | D7: 1800 | E7: LightHouse | F7: =SUMIF('Sales Data'!D7:D36, Products!A7, 'Sales Data'!H7:H36) -> 12

Sheet Customers
A1: Customer_ID | B1: Customer_Name | C1: Age | D1: Gender | E1: City | F1: Customer_Segment
A2: CUST001 | B2: Aarav Sharma | C2: 28 | D2: Male | E2: Ahmedabad | F2: Premium
A3: CUST002 | B3: Diya Patel | C3: 34 | D3: Female | E3: Mumbai | F3: Regular
A4: CUST003 | B4: Rohan Mehta | C4: 25 | D4: Male | E4: Bangalore | F4: New
A5: CUST004 | B5: Ananya Shah | C5: 41 | D5: Female | E5: Delhi | F5: Premium
A6: CUST005 | B6: Vivaan Desai | C6: 30 | D6: Male | E6: Pune | F6: Regular
A7: CUST006 | B7: Ishita Joshi | C7: 26 | D7: Female | E7: Ahmedabad | F7: New
A8: CUST007 | B8: Arjun Kapoor | C8: 38 | D8: Male | E8: Jaipur | F8: Premium
A9: CUST008 | B9: Meera Rao | C9: 29 | D9: Female | E9: Hyderabad | F9: Regular
A10: CUST009 | B10: Kabir Singh | C10: 45 | D10: Male | E10: Chandigarh | F10: Premium
A11: CUST010 | B11: Sara Khan | C11: 32 | D11: Female | E11: Kolkata | F11: Regular
